postgres_mcp_pro_plus/__init__.py
postgres_mcp_pro_plus/artifacts.py
postgres_mcp_pro_plus/blocking_queries.py
postgres_mcp_pro_plus/database_overview.py
postgres_mcp_pro_plus/schema_mapping.py
postgres_mcp_pro_plus/server.py
postgres_mcp_pro_plus/vacuum_analysis.py
postgres_mcp_pro_plus/database_health/__init__.py
postgres_mcp_pro_plus/database_health/buffer_health_calc.py
postgres_mcp_pro_plus/database_health/connection_health_calc.py
postgres_mcp_pro_plus/database_health/constraint_health_calc.py
postgres_mcp_pro_plus/database_health/database_health.py
postgres_mcp_pro_plus/database_health/index_health_calc.py
postgres_mcp_pro_plus/database_health/replication_calc.py
postgres_mcp_pro_plus/database_health/sequence_health_calc.py
postgres_mcp_pro_plus/database_health/vacuum_health_calc.py
postgres_mcp_pro_plus/explain/README.md
postgres_mcp_pro_plus/explain/__init__.py
postgres_mcp_pro_plus/explain/explain_plan.py
postgres_mcp_pro_plus/index/dta_calc.py
postgres_mcp_pro_plus/index/index_opt_base.py
postgres_mcp_pro_plus/index/llm_opt.py
postgres_mcp_pro_plus/index/presentation.py
postgres_mcp_pro_plus/sql/__init__.py
postgres_mcp_pro_plus/sql/bind_params.py
postgres_mcp_pro_plus/sql/extension_utils.py
postgres_mcp_pro_plus/sql/index.py
postgres_mcp_pro_plus/sql/safe_sql.py
postgres_mcp_pro_plus/sql/sql_driver.py
postgres_mcp_pro_plus/top_queries/__init__.py
postgres_mcp_pro_plus/top_queries/top_queries_calc.py
postgres_mcp_pro_plus-0.4.4.dist-info/METADATA
postgres_mcp_pro_plus-0.4.4.dist-info/WHEEL
postgres_mcp_pro_plus-0.4.4.dist-info/entry_points.txt
postgres_mcp_pro_plus-0.4.4.dist-info/licenses/LICENSE
postgres_mcp_pro_plus-0.4.4.dist-info/RECORD
