Metadata-Version: 2.4
Name: postgres-mcp-pro-plus
Version: 0.4.4
Summary: PostgreSQL Tuning and Analysis Tool
Author-email: Johann Schleier-Smith <jssmith@crystal.cloud>, "Henry (Duc) Bui" <henry.bmduc@gmail.com>
License-Expression: MIT
License-File: LICENSE
Requires-Python: >=3.12
Requires-Dist: attrs>=25.3.0
Requires-Dist: humanize>=4.8.0
Requires-Dist: instructor>=1.7.9
Requires-Dist: mcp[cli]>=1.5.0
Requires-Dist: pglast==7.2.0
Requires-Dist: pre-commit>=4.2.0
Requires-Dist: psycopg-pool>=3.2.6
Requires-Dist: psycopg[binary]>=3.2.6
Requires-Dist: python-dotenv>=1.1.0
